{
	"configurations" : 
	[
		{
			"directories" : 
			[
				{
					"build" : ".",
					"childIndexes" : 
					[
						1,
						2,
						3,
						5,
						6,
						7,
						9,
						12
					],
					"hasInstallRule" : true,
					"jsonFile" : "directory-.-Debug-d0094a50bb2071803777.json",
					"minimumCMakeVersion" : 
					{
						"string" : "3.16"
					},
					"projectIndex" : 0,
					"source" : ".",
					"targetIndexes" : 
					[
						0,
						1,
						2,
						3,
						10
					]
				},
				{
					"build" : "_deps/sdl2-build",
					"jsonFile" : "directory-_deps.sdl2-build-Debug-647eb24766197b9ce204.json",
					"minimumCMakeVersion" : 
					{
						"string" : "3.4"
					},
					"parentIndex" : 0,
					"projectIndex" : 1,
					"source" : "lib/sdl2",
					"targetIndexes" : 
					[
						4,
						7,
						9,
						22,
						27
					]
				},
				{
					"build" : "_deps/sdl2_image-build",
					"jsonFile" : "directory-_deps.sdl2_image-build-Debug-292e232fe68beb5e5486.json",
					"minimumCMakeVersion" : 
					{
						"string" : "3.16"
					},
					"parentIndex" : 0,
					"projectIndex" : 2,
					"source" : "lib/sdl2_image",
					"targetIndexes" : 
					[
						5,
						23,
						25
					]
				},
				{
					"build" : "_deps/sdl2_ttf-build",
					"childIndexes" : 
					[
						4
					],
					"hasInstallRule" : true,
					"jsonFile" : "directory-_deps.sdl2_ttf-build-Debug-f7772deb6a247e855968.json",
					"minimumCMakeVersion" : 
					{
						"string" : "3.14"
					},
					"parentIndex" : 0,
					"projectIndex" : 3,
					"source" : "lib/sdl2_ttf",
					"targetIndexes" : 
					[
						8,
						15,
						24
					]
				},
				{
					"build" : "_deps/sdl2_ttf-build/external/freetype",
					"hasInstallRule" : true,
					"jsonFile" : "directory-_deps.sdl2_ttf-build.external.freetype-Debug-98aa193488cd468c6e1a.json",
					"minimumCMakeVersion" : 
					{
						"string" : "3.0"
					},
					"parentIndex" : 3,
					"projectIndex" : 4,
					"source" : "lib/sdl2_ttf/external/freetype",
					"targetIndexes" : 
					[
						11
					]
				},
				{
					"build" : "_deps/sdl2_mixer-build",
					"jsonFile" : "directory-_deps.sdl2_mixer-build-Debug-87816ebfe9679ab9fe3c.json",
					"minimumCMakeVersion" : 
					{
						"string" : "3.16"
					},
					"parentIndex" : 0,
					"projectIndex" : 5,
					"source" : "lib/sdl2_mixer",
					"targetIndexes" : 
					[
						6,
						20,
						21
					]
				},
				{
					"build" : "_deps/spdlog-build",
					"jsonFile" : "directory-_deps.spdlog-build-Debug-f665232a9e6e76e72208.json",
					"minimumCMakeVersion" : 
					{
						"string" : "3.10"
					},
					"parentIndex" : 0,
					"projectIndex" : 6,
					"source" : "lib/spdlog",
					"targetIndexes" : 
					[
						26
					]
				},
				{
					"build" : "_deps/glm-build",
					"childIndexes" : 
					[
						8
					],
					"jsonFile" : "directory-_deps.glm-build-Debug-50f54b216b0daf3f9de3.json",
					"minimumCMakeVersion" : 
					{
						"string" : "3.2"
					},
					"parentIndex" : 0,
					"projectIndex" : 7,
					"source" : "lib/glm"
				},
				{
					"build" : "_deps/glm-build/glm",
					"jsonFile" : "directory-_deps.glm-build.glm-Debug-bcf8cf7510abb64fe405.json",
					"minimumCMakeVersion" : 
					{
						"string" : "3.2"
					},
					"parentIndex" : 7,
					"projectIndex" : 7,
					"source" : "lib/glm/glm"
				},
				{
					"build" : "_deps/googletest-build",
					"childIndexes" : 
					[
						10
					],
					"hasInstallRule" : true,
					"jsonFile" : "directory-_deps.googletest-build-Debug-ca310e4ee65ccb0210f7.json",
					"minimumCMakeVersion" : 
					{
						"string" : "3.5"
					},
					"parentIndex" : 0,
					"projectIndex" : 8,
					"source" : "lib/googletest"
				},
				{
					"build" : "_deps/googletest-build/googlemock",
					"childIndexes" : 
					[
						11
					],
					"hasInstallRule" : true,
					"jsonFile" : "directory-_deps.googletest-build.googlemock-Debug-f2b97b001c8fed42ea84.json",
					"minimumCMakeVersion" : 
					{
						"string" : "3.5"
					},
					"parentIndex" : 9,
					"projectIndex" : 9,
					"source" : "lib/googletest/googlemock",
					"targetIndexes" : 
					[
						16,
						17
					]
				},
				{
					"build" : "_deps/googletest-build/googletest",
					"hasInstallRule" : true,
					"jsonFile" : "directory-_deps.googletest-build.googletest-Debug-db446146c0567e122cc4.json",
					"minimumCMakeVersion" : 
					{
						"string" : "3.5"
					},
					"parentIndex" : 10,
					"projectIndex" : 10,
					"source" : "lib/googletest/googletest",
					"targetIndexes" : 
					[
						18,
						19
					]
				},
				{
					"build" : "lib/glew/build/cmake",
					"hasInstallRule" : true,
					"jsonFile" : "directory-lib.glew.build.cmake-Debug-8dde41f726773b954339.json",
					"minimumCMakeVersion" : 
					{
						"string" : "2.8.12"
					},
					"parentIndex" : 0,
					"projectIndex" : 11,
					"source" : "lib/glew/build/cmake",
					"targetIndexes" : 
					[
						12,
						13,
						14,
						28
					]
				}
			],
			"name" : "Debug",
			"projects" : 
			[
				{
					"childIndexes" : 
					[
						1,
						2,
						3,
						5,
						6,
						7,
						8,
						11
					],
					"directoryIndexes" : 
					[
						0
					],
					"name" : "PracticalToolsForSimpleDesign",
					"targetIndexes" : 
					[
						0,
						1,
						2,
						3,
						10
					]
				},
				{
					"directoryIndexes" : 
					[
						1
					],
					"name" : "SDL2",
					"parentIndex" : 0,
					"targetIndexes" : 
					[
						4,
						7,
						9,
						22,
						27
					]
				},
				{
					"directoryIndexes" : 
					[
						2
					],
					"name" : "SDL2_image",
					"parentIndex" : 0,
					"targetIndexes" : 
					[
						5,
						23,
						25
					]
				},
				{
					"childIndexes" : 
					[
						4
					],
					"directoryIndexes" : 
					[
						3
					],
					"name" : "SDL2_ttf",
					"parentIndex" : 0,
					"targetIndexes" : 
					[
						8,
						15,
						24
					]
				},
				{
					"directoryIndexes" : 
					[
						4
					],
					"name" : "freetype",
					"parentIndex" : 3,
					"targetIndexes" : 
					[
						11
					]
				},
				{
					"directoryIndexes" : 
					[
						5
					],
					"name" : "SDL2_mixer",
					"parentIndex" : 0,
					"targetIndexes" : 
					[
						6,
						20,
						21
					]
				},
				{
					"directoryIndexes" : 
					[
						6
					],
					"name" : "spdlog",
					"parentIndex" : 0,
					"targetIndexes" : 
					[
						26
					]
				},
				{
					"directoryIndexes" : 
					[
						7,
						8
					],
					"name" : "glm",
					"parentIndex" : 0
				},
				{
					"childIndexes" : 
					[
						9
					],
					"directoryIndexes" : 
					[
						9
					],
					"name" : "googletest-distribution",
					"parentIndex" : 0
				},
				{
					"childIndexes" : 
					[
						10
					],
					"directoryIndexes" : 
					[
						10
					],
					"name" : "gmock",
					"parentIndex" : 8,
					"targetIndexes" : 
					[
						16,
						17
					]
				},
				{
					"directoryIndexes" : 
					[
						11
					],
					"name" : "gtest",
					"parentIndex" : 9,
					"targetIndexes" : 
					[
						18,
						19
					]
				},
				{
					"directoryIndexes" : 
					[
						12
					],
					"name" : "glew",
					"parentIndex" : 0,
					"targetIndexes" : 
					[
						12,
						13,
						14,
						28
					]
				}
			],
			"targets" : 
			[
				{
					"directoryIndex" : 0,
					"id" : "AudioTest::@6890427a1f51a3e7e1df",
					"jsonFile" : "target-AudioTest-Debug-1142c857c62ce674bc2c.json",
					"name" : "AudioTest",
					"projectIndex" : 0
				},
				{
					"directoryIndex" : 0,
					"id" : "Example::@6890427a1f51a3e7e1df",
					"jsonFile" : "target-Example-Debug-a13407a652b3992547bc.json",
					"name" : "Example",
					"projectIndex" : 0
				},
				{
					"directoryIndex" : 0,
					"id" : "ImGui::@6890427a1f51a3e7e1df",
					"jsonFile" : "target-ImGui-Debug-e5cdac039459c4204291.json",
					"name" : "ImGui",
					"projectIndex" : 0
				},
				{
					"directoryIndex" : 0,
					"id" : "PTSD::@6890427a1f51a3e7e1df",
					"jsonFile" : "target-PTSD-Debug-cdf842083936b3582387.json",
					"name" : "PTSD",
					"projectIndex" : 0
				},
				{
					"directoryIndex" : 1,
					"id" : "SDL2-static::@45bd952f1071c035638d",
					"jsonFile" : "target-SDL2-static-Debug-f01a6f29ec8b244f4f19.json",
					"name" : "SDL2-static",
					"projectIndex" : 1
				},
				{
					"directoryIndex" : 2,
					"id" : "SDL2_image::@de341d98faad78faee90",
					"jsonFile" : "target-SDL2_image-Debug-35ae4a3ec0759347c7a4.json",
					"name" : "SDL2_image",
					"projectIndex" : 2
				},
				{
					"directoryIndex" : 5,
					"id" : "SDL2_mixer::@82d5866ba632f3b21364",
					"jsonFile" : "target-SDL2_mixer-Debug-6a84b8de2b7178b1b81f.json",
					"name" : "SDL2_mixer",
					"projectIndex" : 5
				},
				{
					"directoryIndex" : 1,
					"id" : "SDL2_test::@45bd952f1071c035638d",
					"jsonFile" : "target-SDL2_test-Debug-c37a3c7e46d20ce67f21.json",
					"name" : "SDL2_test",
					"projectIndex" : 1
				},
				{
					"directoryIndex" : 3,
					"id" : "SDL2_ttf::@bbdb2daa5afc341778ea",
					"jsonFile" : "target-SDL2_ttf-Debug-c1e74fe5564c55441406.json",
					"name" : "SDL2_ttf",
					"projectIndex" : 3
				},
				{
					"directoryIndex" : 1,
					"id" : "SDL2main::@45bd952f1071c035638d",
					"jsonFile" : "target-SDL2main-Debug-37a499f8014730dde41a.json",
					"name" : "SDL2main",
					"projectIndex" : 1
				},
				{
					"directoryIndex" : 0,
					"id" : "Tests::@6890427a1f51a3e7e1df",
					"jsonFile" : "target-Tests-Debug-a21a0c47c238789af781.json",
					"name" : "Tests",
					"projectIndex" : 0
				},
				{
					"directoryIndex" : 4,
					"id" : "freetype::@1caf39cd73602fb8f135",
					"jsonFile" : "target-freetype-Debug-8f006c8b5433f0227d6b.json",
					"name" : "freetype",
					"projectIndex" : 4
				},
				{
					"directoryIndex" : 12,
					"id" : "glew::@b46fb324963b76809ed6",
					"jsonFile" : "target-glew-Debug-cbdee49308085433f325.json",
					"name" : "glew",
					"projectIndex" : 11
				},
				{
					"directoryIndex" : 12,
					"id" : "glew_s::@b46fb324963b76809ed6",
					"jsonFile" : "target-glew_s-Debug-943bffd58547a821e72c.json",
					"name" : "glew_s",
					"projectIndex" : 11
				},
				{
					"directoryIndex" : 12,
					"id" : "glewinfo::@b46fb324963b76809ed6",
					"jsonFile" : "target-glewinfo-Debug-f05d3dbb33c339a43b78.json",
					"name" : "glewinfo",
					"projectIndex" : 11
				},
				{
					"directoryIndex" : 3,
					"id" : "glfont::@bbdb2daa5afc341778ea",
					"jsonFile" : "target-glfont-Debug-2a7f01b90f6f8dbcb2da.json",
					"name" : "glfont",
					"projectIndex" : 3
				},
				{
					"directoryIndex" : 10,
					"id" : "gmock::@0f7bb11d64f3678238c7",
					"jsonFile" : "target-gmock-Debug-70f844d9221b3e9d9e0e.json",
					"name" : "gmock",
					"projectIndex" : 9
				},
				{
					"directoryIndex" : 10,
					"id" : "gmock_main::@0f7bb11d64f3678238c7",
					"jsonFile" : "target-gmock_main-Debug-9aba4f0b2a9c3623245b.json",
					"name" : "gmock_main",
					"projectIndex" : 9
				},
				{
					"directoryIndex" : 11,
					"id" : "gtest::@1ea2dfc0605fe3ab2a3f",
					"jsonFile" : "target-gtest-Debug-f6a8cecbe3511a2ec30d.json",
					"name" : "gtest",
					"projectIndex" : 10
				},
				{
					"directoryIndex" : 11,
					"id" : "gtest_main::@1ea2dfc0605fe3ab2a3f",
					"jsonFile" : "target-gtest_main-Debug-6cd85bf79cd322976cf7.json",
					"name" : "gtest_main",
					"projectIndex" : 10
				},
				{
					"directoryIndex" : 5,
					"id" : "playmus::@82d5866ba632f3b21364",
					"jsonFile" : "target-playmus-Debug-0c555d952912ecab2ae4.json",
					"name" : "playmus",
					"projectIndex" : 5
				},
				{
					"directoryIndex" : 5,
					"id" : "playwave::@82d5866ba632f3b21364",
					"jsonFile" : "target-playwave-Debug-2fd31a45e702c3ba4b94.json",
					"name" : "playwave",
					"projectIndex" : 5
				},
				{
					"directoryIndex" : 1,
					"id" : "sdl_headers_copy::@45bd952f1071c035638d",
					"jsonFile" : "target-sdl_headers_copy-Debug-c9252f8f1f387bd8a6f3.json",
					"name" : "sdl_headers_copy",
					"projectIndex" : 1
				},
				{
					"directoryIndex" : 2,
					"id" : "showanim::@de341d98faad78faee90",
					"jsonFile" : "target-showanim-Debug-75c993626df7b2ac2cdb.json",
					"name" : "showanim",
					"projectIndex" : 2
				},
				{
					"directoryIndex" : 3,
					"id" : "showfont::@bbdb2daa5afc341778ea",
					"jsonFile" : "target-showfont-Debug-dbef25ba513ed184580a.json",
					"name" : "showfont",
					"projectIndex" : 3
				},
				{
					"directoryIndex" : 2,
					"id" : "showimage::@de341d98faad78faee90",
					"jsonFile" : "target-showimage-Debug-4c05a8f4f3045b1d0e2a.json",
					"name" : "showimage",
					"projectIndex" : 2
				},
				{
					"directoryIndex" : 6,
					"id" : "spdlog::@eb35cfce7893ccfeff1e",
					"jsonFile" : "target-spdlog-Debug-6ff70f3fce852489765a.json",
					"name" : "spdlog",
					"projectIndex" : 6
				},
				{
					"directoryIndex" : 1,
					"id" : "uninstall::@45bd952f1071c035638d",
					"jsonFile" : "target-uninstall-Debug-352c329018607d1e8518.json",
					"name" : "uninstall",
					"projectIndex" : 1
				},
				{
					"directoryIndex" : 12,
					"id" : "visualinfo::@b46fb324963b76809ed6",
					"jsonFile" : "target-visualinfo-Debug-a2e5c6c906fab816d367.json",
					"name" : "visualinfo",
					"projectIndex" : 11
				}
			]
		}
	],
	"kind" : "codemodel",
	"paths" : 
	{
		"build" : "C:/Users/Billy/Desktop/oop_project/Slay-the-Spire/build",
		"source" : "C:/Users/Billy/Desktop/oop_project/Slay-the-Spire/PTSD"
	},
	"version" : 
	{
		"major" : 2,
		"minor" : 8
	}
}
